engine/__init__.py
engine/exceptions.py
engine/help.py
engine_python-1.9.0.dist-info/licenses/LICENSE
engine_python-1.9.0.dist-info/METADATA
engine_python-1.9.0.dist-info/WHEEL
engine_python-1.9.0.dist-info/top_level.txt
engine_python-1.9.0.dist-info/RECORD
