Metadata-Version: 2.4
Name: engine-python
Version: 1.9.0
Summary: An intelligent, asynchronous search engine library for Python
Home-page: https://github.com/kissmeBro/engine-python
Author: stone
Author-email: kissme.cloud@example.com
License: MIT
Keywords: search,async,engine,aiohttp,engine-python,google
Classifier: Programming Language :: Python :: 3
Classifier: Operating System :: OS Independent
Classifier: Framework :: AsyncIO
Classifier: Topic :: Software Development :: Libraries :: Python Modules
Requires-Python: >=3.9
License-File: LICENSE
Requires-Dist: aiohttp
Dynamic: author
Dynamic: author-email
Dynamic: classifier
Dynamic: description
Dynamic: description-content-type
Dynamic: home-page
Dynamic: keywords
Dynamic: license
Dynamic: license-file
Dynamic: requires-dist
Dynamic: requires-python
Dynamic: summary
